README.rst
setup.cfg
setup.py
pyssb/__init__.py
pyssb/pyssb.py
pyssb.egg-info/PKG-INFO
pyssb.egg-info/SOURCES.txt
pyssb.egg-info/dependency_links.txt
pyssb.egg-info/requires.txt
pyssb.egg-info/top_level.txt