Metadata-Version: 1.1
Name: pyssb
Version: 0.1.1
Summary: PyQT5 Site Specific Browser
Home-page: https://github.com/lhl/pyssb
Author: Leonard Lin
Author-email: lhl@randomfoo.net
License: UNKNOWN
Download-URL: https://github.com/lhl/pyssb/archive/master.zip
Keywords: browser,ssb
Platform: UNKNOWN
